<?xml version="1.0" encoding="UTF-8"?>
<!DOCTYPE suite SYSTEM "http://testng.org/testng-1.0.dtd">
<suite configfailurepolicy="continue" guice-stage="DEVELOPMENT" verbose="10" name="Failed suite [TC_001]" parallel="tests">
  <parameter name="browser" value="safari"/>
  <listeners>
    <listener class-name="com.setup.TestNGListener"/>
  </listeners>
  <test thread-count="5" verbose="10" name="TC_01_Example(failed)" parallel="tests">
    <classes>
      <class name="com.test.TC_04_AmelcoAPI.ID_04_PlaceBet">
        <methods>
          <include name="report"/>
          <include name="startTest"/>
          <include name="setup"/>
          <include name="clearXml"/>
          <include name="tearDown"/>
          <include name="placeBet" invocation-numbers="0"/>
        </methods>
      </class> <!-- com.test.TC_04_AmelcoAPI.ID_04_PlaceBet -->
      <class name="com.test.TC_04_AmelcoAPI.ID_03_GetOpenBets">
        <methods>
          <include name="report"/>
          <include name="setup"/>
          <include name="clearXml"/>
          <include name="tearDown"/>
          <include name="startTest"/>
          <include name="getOpenBets" invocation-numbers="0"/>
        </methods>
      </class> <!-- com.test.TC_04_AmelcoAPI.ID_03_GetOpenBets -->
      <class name="com.test.TC_04_AmelcoAPI.ID_02_ExternalLogin">
        <methods>
          <include name="report"/>
          <include name="externalLogin" invocation-numbers="0"/>
          <include name="setup"/>
          <include name="clearXml"/>
          <include name="tearDown"/>
          <include name="startTest"/>
        </methods>
      </class> <!-- com.test.TC_04_AmelcoAPI.ID_02_ExternalLogin -->
    </classes>
  </test> <!-- TC_01_Example(failed) -->
</suite> <!-- Failed suite [TC_001] -->
