{
  "requestid": "0",
  "series": [
    {
      "expires": "2020-02-17T18:34:10.4806068+01:00",
      "data": {
        "lastTime": "2020-02-17T17:34:01",
        "highTime": "2020-02-17T09:13:23",
        "windowTrend": -0.00183,
        "openPrice": 1.436115,
        "windowPreviousCloseTime": "2020-02-16T22:59:07",
        "alfa": "CADEU2",
        "type": "VAL",
        "relDiff": -0.00183,
        "cumulativeVolume": 0.0,
        "windowHighTime": "2020-02-17T09:13:00",
        "lowPrice": 1.43305,
        "tradingStartTime": "05:15:00",
        "highPrice": 1.436295,
        "closeTime": "2020-02-16T23:00:00",
        "currency": "CAD",
        "windowEnd": "2020-02-17T17:34:01",
        "windowFirst": "2020-02-17T00:00:00",
        "openTime": "2020-02-16T23:00:00",
        "identifier": "issueid:190168883",
        "issueId": 190168883,
        "windowStart": "2020-02-17T00:00:00",
        "windowLast": "2020-02-17T17:34:00",
        "windowLowPrice": 1.43305,
        "previousCloseTime": "2020-02-16T22:59:07",
        "windowOpenTime": "2020-02-17T00:00:00",
        "tradingEndTime": "22:30:00",
        "quality": "REALTIME",
        "market": "IND",
        "previousClosePrice": 1.436155,
        "windowHighPrice": 1.436295,
        "windowOpenPrice": 1.43596,
        "highPriceP1Y": 1.5223,
        "lowPriceP1Y": 1.4348,
        "tradingAddedTime": "00:02:00",
        "name": "EUR/CAD",
        "windowPreviousClosePrice": 1.436155,
        "absDiff": -0.002635,
        "closePrice": 1.436115,
        "windowLowTime": "2020-02-17T13:11:00",
        "isin": "EU0009654664",
        "lowTime": "2020-02-17T13:11:27",
        "lastPrice": 1.43352
      },
      "id": "issueid:190168883",
      "type": "object"
    },
    {
      "times": "2020-02-17T00:00:00/PT1M",
      "expires": "2020-02-17T18:34:10.4856038+01:00",
      "data": [
        [
          0,
          1.4358
        ],
        [
          1,
          1.4358
        ],
        [
          2,
          1.4356
        ],
        [
          3,
          1.4356
        ],
        [
          4,
          1.4357
        ],
        [
          5,
          1.4358
        ],
        [
          6,
          1.4357
        ],
        [
          7,
          1.4357
        ],
        [
          8,
          1.4357
        ],
        [
          9,
          1.4355
        ],
        [
          10,
          1.4356
        ],
        [
          11,
          1.4357
        ],
        [
          12,
          1.4358
        ],
        [
          13,
          1.4358
        ],
        [
          14,
          1.4358
        ],
        [
          15,
          1.4357
        ],
        [
          16,
          1.4356
        ],
        [
          17,
          1.4356
        ],
        [
          18,
          1.4356
        ],
        [
          19,
          1.4356
        ],
        [
          20,
          1.4356
        ],
        [
          21,
          1.4357
        ],
        [
          22,
          1.4356
        ],
        [
          23,
          1.4356
        ],
        [
          24,
          1.4356
        ],
        [
          25,
          1.4356
        ],
        [
          26,
          1.4356
        ],
        [
          27,
          1.4356
        ],
        [
          28,
          1.4357
        ],
        [
          29,
          1.4357
        ],
        [
          30,
          1.4358
        ],
        [
          31,
          1.4358
        ],
        [
          32,
          1.4358
        ],
        [
          33,
          1.4358
        ],
        [
          34,
          1.4358
        ],
        [
          35,
          1.4358
        ],
        [
          36,
          1.4358
        ],
        [
          37,
          1.4358
        ],
        [
          38,
          1.4357
        ],
        [
          39,
          1.4356
        ],
        [
          40,
          1.4357
        ],
        [
          41,
          1.4356
        ],
        [
          42,
          1.4356
        ],
        [
          43,
          1.4357
        ],
        [
          44,
          1.4357
        ],
        [
          45,
          1.4357
        ],
        [
          46,
          1.4358
        ],
        [
          47,
          1.4357
        ],
        [
          48,
          1.4358
        ],
        [
          49,
          1.4358
        ],
        [
          50,
          1.4358
        ],
        [
          51,
          1.4358
        ],
        [
          52,
          1.4357
        ],
        [
          53,
          1.4357
        ],
        [
          54,
          1.4357
        ],
        [
          55,
          1.4357
        ],
        [
          56,
          1.4357
        ],
        [
          57,
          1.4357
        ],
        [
          58,
          1.4357
        ],
        [
          59,
          1.4357
        ],
        [
          60,
          1.4357
        ],
        [
          61,
          1.4357
        ],
        [
          62,
          1.4356
        ],
        [
          63,
          1.4355
        ],
        [
          64,
          1.4355
        ],
        [
          65,
          1.4357
        ],
        [
          66,
          1.4357
        ],
        [
          67,
          1.4358
        ],
        [
          68,
          1.4359
        ],
        [
          69,
          1.4358
        ],
        [
          70,
          1.4356
        ],
        [
          71,
          1.4356
        ],
        [
          72,
          1.4356
        ],
        [
          73,
          1.4356
        ],
        [
          74,
          1.4356
        ],
        [
          75,
          1.4354
        ],
        [
          76,
          1.4353
        ],
        [
          77,
          1.4353
        ],
        [
          78,
          1.4352
        ],
        [
          79,
          1.4352
        ],
        [
          80,
          1.4352
        ],
        [
          81,
          1.4351
        ],
        [
          82,
          1.4352
        ],
        [
          83,
          1.4352
        ],
        [
          84,
          1.4352
        ],
        [
          85,
          1.4352
        ],
        [
          86,
          1.4352
        ],
        [
          87,
          1.4352
        ],
        [
          88,
          1.4352
        ],
        [
          89,
          1.4353
        ],
        [
          90,
          1.4353
        ],
        [
          91,
          1.4353
        ],
        [
          92,
          1.4353
        ],
        [
          93,
          1.4352
        ],
        [
          94,
          1.4352
        ],
        [
          95,
          1.4352
        ],
        [
          96,
          1.4352
        ],
        [
          97,
          1.4352
        ],
        [
          98,
          1.4352
        ],
        [
          99,
          1.4352
        ],
        [
          100,
          1.4353
        ],
        [
          101,
          1.4353
        ],
        [
          102,
          1.4353
        ],
        [
          103,
          1.4353
        ],
        [
          104,
          1.4354
        ],
        [
          105,
          1.4354
        ],
        [
          106,
          1.4354
        ],
        [
          107,
          1.4353
        ],
        [
          108,
          1.4354
        ],
        [
          109,
          1.4353
        ],
        [
          110,
          1.4353
        ],
        [
          111,
          1.4353
        ],
        [
          112,
          1.4353
        ],
        [
          113,
          1.4353
        ],
        [
          114,
          1.4352
        ],
        [
          115,
          1.4351
        ],
        [
          116,
          1.4352
        ],
        [
          117,
          1.4351
        ],
        [
          118,
          1.4351
        ],
        [
          119,
          1.4351
        ],
        [
          120,
          1.4351
        ],
        [
          121,
          1.4351
        ],
        [
          122,
          1.4351
        ],
        [
          123,
          1.4352
        ],
        [
          124,
          1.4351
        ],
        [
          125,
          1.4353
        ],
        [
          126,
          1.4352
        ],
        [
          127,
          1.4352
        ],
        [
          128,
          1.4353
        ],
        [
          129,
          1.4352
        ],
        [
          130,
          1.4352
        ],
        [
          131,
          1.4352
        ],
        [
          132,
          1.4352
        ],
        [
          133,
          1.4353
        ],
        [
          134,
          1.4353
        ],
        [
          135,
          1.4352
        ],
        [
          136,
          1.4352
        ],
        [
          137,
          1.4352
        ],
        [
          138,
          1.4352
        ],
        [
          139,
          1.4352
        ],
        [
          140,
          1.4352
        ],
        [
          141,
          1.4352
        ],
        [
          142,
          1.4352
        ],
        [
          143,
          1.4352
        ],
        [
          144,
          1.4352
        ],
        [
          145,
          1.4352
        ],
        [
          146,
          1.4352
        ],
        [
          147,
          1.4352
        ],
        [
          148,
          1.4353
        ],
        [
          149,
          1.4352
        ],
        [
          150,
          1.4352
        ],
        [
          151,
          1.4353
        ],
        [
          152,
          1.4352
        ],
        [
          153,
          1.4352
        ],
        [
          154,
          1.4353
        ],
        [
          155,
          1.4352
        ],
        [
          156,
          1.4352
        ],
        [
          157,
          1.4352
        ],
        [
          158,
          1.4351
        ],
        [
          159,
          1.4352
        ],
        [
          160,
          1.4351
        ],
        [
          161,
          1.4352
        ],
        [
          162,
          1.4351
        ],
        [
          163,
          1.435
        ],
        [
          164,
          1.4351
        ],
        [
          165,
          1.4351
        ],
        [
          166,
          1.4351
        ],
        [
          167,
          1.4351
        ],
        [
          168,
          1.4351
        ],
        [
          169,
          1.4349
        ],
        [
          170,
          1.435
        ],
        [
          171,
          1.4349
        ],
        [
          172,
          1.435
        ],
        [
          173,
          1.4349
        ],
        [
          174,
          1.4349
        ],
        [
          175,
          1.435
        ],
        [
          176,
          1.4349
        ],
        [
          177,
          1.4349
        ],
        [
          178,
          1.4349
        ],
        [
          179,
          1.4348
        ],
        [
          180,
          1.4348
        ],
        [
          181,
          1.4347
        ],
        [
          182,
          1.4347
        ],
        [
          183,
          1.4348
        ],
        [
          184,
          1.4347
        ],
        [
          185,
          1.4347
        ],
        [
          186,
          1.4347
        ],
        [
          187,
          1.4346
        ],
        [
          188,
          1.4347
        ],
        [
          189,
          1.4346
        ],
        [
          190,
          1.4347
        ],
        [
          191,
          1.4347
        ],
        [
          192,
          1.4347
        ],
        [
          193,
          1.4347
        ],
        [
          194,
          1.4347
        ],
        [
          195,
          1.4347
        ],
        [
          196,
          1.4347
        ],
        [
          197,
          1.4347
        ],
        [
          198,
          1.4348
        ],
        [
          199,
          1.4348
        ],
        [
          200,
          1.4347
        ],
        [
          201,
          1.4347
        ],
        [
          202,
          1.4348
        ],
        [
          203,
          1.4347
        ],
        [
          204,
          1.4347
        ],
        [
          205,
          1.4347
        ],
        [
          206,
          1.4346
        ],
        [
          207,
          1.4347
        ],
        [
          208,
          1.4347
        ],
        [
          209,
          1.4347
        ],
        [
          210,
          1.4347
        ],
        [
          211,
          1.4347
        ],
        [
          212,
          1.4347
        ],
        [
          213,
          1.4347
        ],
        [
          214,
          1.4347
        ],
        [
          215,
          1.4347
        ],
        [
          216,
          1.4347
        ],
        [
          217,
          1.4347
        ],
        [
          218,
          1.4347
        ],
        [
          219,
          1.4346
        ],
        [
          220,
          1.4347
        ],
        [
          221,
          1.4347
        ],
        [
          222,
          1.4347
        ],
        [
          223,
          1.4347
        ],
        [
          224,
          1.4347
        ],
        [
          225,
          1.4347
        ],
        [
          226,
          1.4348
        ],
        [
          227,
          1.4347
        ],
        [
          228,
          1.4347
        ],
        [
          229,
          1.4347
        ],
        [
          230,
          1.4347
        ],
        [
          231,
          1.4347
        ],
        [
          232,
          1.4347
        ],
        [
          233,
          1.4347
        ],
        [
          234,
          1.4347
        ],
        [
          235,
          1.4346
        ],
        [
          236,
          1.4346
        ],
        [
          237,
          1.4347
        ],
        [
          238,
          1.4347
        ],
        [
          239,
          1.4347
        ],
        [
          240,
          1.4347
        ],
        [
          241,
          1.4348
        ],
        [
          242,
          1.4348
        ],
        [
          243,
          1.4348
        ],
        [
          244,
          1.4348
        ],
        [
          245,
          1.4348
        ],
        [
          246,
          1.4348
        ],
        [
          247,
          1.4347
        ],
        [
          248,
          1.4349
        ],
        [
          249,
          1.4349
        ],
        [
          250,
          1.4349
        ],
        [
          251,
          1.4349
        ],
        [
          252,
          1.4349
        ],
        [
          253,
          1.435
        ],
        [
          254,
          1.435
        ],
        [
          255,
          1.4349
        ],
        [
          256,
          1.4349
        ],
        [
          257,
          1.4349
        ],
        [
          258,
          1.435
        ],
        [
          259,
          1.435
        ],
        [
          260,
          1.435
        ],
        [
          261,
          1.4349
        ],
        [
          262,
          1.4347
        ],
        [
          263,
          1.4348
        ],
        [
          264,
          1.4348
        ],
        [
          265,
          1.4348
        ],
        [
          266,
          1.4349
        ],
        [
          267,
          1.4349
        ],
        [
          268,
          1.4349
        ],
        [
          269,
          1.4348
        ],
        [
          270,
          1.4348
        ],
        [
          271,
          1.4348
        ],
        [
          272,
          1.4348
        ],
        [
          273,
          1.4349
        ],
        [
          274,
          1.4348
        ],
        [
          275,
          1.4348
        ],
        [
          276,
          1.4348
        ],
        [
          277,
          1.4349
        ],
        [
          278,
          1.4349
        ],
        [
          279,
          1.4348
        ],
        [
          280,
          1.4348
        ],
        [
          281,
          1.4348
        ],
        [
          282,
          1.4348
        ],
        [
          283,
          1.4348
        ],
        [
          284,
          1.4349
        ],
        [
          285,
          1.4348
        ],
        [
          286,
          1.4349
        ],
        [
          287,
          1.4348
        ],
        [
          288,
          1.4348
        ],
        [
          289,
          1.4349
        ],
        [
          290,
          1.4348
        ],
        [
          291,
          1.4349
        ],
        [
          292,
          1.4349
        ],
        [
          293,
          1.4348
        ],
        [
          294,
          1.4348
        ],
        [
          295,
          1.4348
        ],
        [
          296,
          1.4347
        ],
        [
          297,
          1.4348
        ],
        [
          298,
          1.4348
        ],
        [
          299,
          1.4347
        ],
        [
          300,
          1.4348
        ],
        [
          301,
          1.4348
        ],
        [
          302,
          1.4348
        ],
        [
          303,
          1.4347
        ],
        [
          304,
          1.4347
        ],
        [
          305,
          1.4347
        ],
        [
          306,
          1.4347
        ],
        [
          307,
          1.4347
        ],
        [
          308,
          1.4347
        ],
        [
          309,
          1.4347
        ],
        [
          310,
          1.4348
        ],
        [
          311,
          1.4348
        ],
        [
          312,
          1.4348
        ],
        [
          313,
          1.4347
        ],
        [
          314,
          1.4347
        ],
        [
          315,
          1.4348
        ],
        [
          316,
          1.4348
        ],
        [
          317,
          1.4348
        ],
        [
          318,
          1.4347
        ],
        [
          319,
          1.4347
        ],
        [
          320,
          1.4347
        ],
        [
          321,
          1.4347
        ],
        [
          322,
          1.4348
        ],
        [
          323,
          1.4348
        ],
        [
          324,
          1.4348
        ],
        [
          325,
          1.4347
        ],
        [
          326,
          1.4347
        ],
        [
          327,
          1.4347
        ],
        [
          328,
          1.4346
        ],
        [
          329,
          1.4346
        ],
        [
          330,
          1.4346
        ],
        [
          331,
          1.4347
        ],
        [
          332,
          1.4346
        ],
        [
          333,
          1.4347
        ],
        [
          334,
          1.4346
        ],
        [
          335,
          1.4347
        ],
        [
          336,
          1.4346
        ],
        [
          337,
          1.4347
        ],
        [
          338,
          1.4347
        ],
        [
          339,
          1.4347
        ],
        [
          340,
          1.4347
        ],
        [
          341,
          1.4346
        ],
        [
          342,
          1.4347
        ],
        [
          343,
          1.4346
        ],
        [
          344,
          1.4346
        ],
        [
          345,
          1.4346
        ],
        [
          346,
          1.4346
        ],
        [
          347,
          1.4346
        ],
        [
          348,
          1.4345
        ],
        [
          349,
          1.4346
        ],
        [
          350,
          1.4346
        ],
        [
          351,
          1.4346
        ],
        [
          352,
          1.4347
        ],
        [
          353,
          1.4347
        ],
        [
          354,
          1.4347
        ],
        [
          355,
          1.4347
        ],
        [
          356,
          1.4347
        ],
        [
          357,
          1.4348
        ],
        [
          358,
          1.4346
        ],
        [
          359,
          1.4346
        ],
        [
          360,
          1.4347
        ],
        [
          361,
          1.4346
        ],
        [
          362,
          1.4347
        ],
        [
          363,
          1.4348
        ],
        [
          364,
          1.4348
        ],
        [
          365,
          1.4348
        ],
        [
          366,
          1.4347
        ],
        [
          367,
          1.4347
        ],
        [
          368,
          1.4346
        ],
        [
          369,
          1.4347
        ],
        [
          370,
          1.4346
        ],
        [
          371,
          1.4346
        ],
        [
          372,
          1.4347
        ],
        [
          373,
          1.4347
        ],
        [
          374,
          1.4347
        ],
        [
          375,
          1.4347
        ],
        [
          376,
          1.4347
        ],
        [
          377,
          1.4347
        ],
        [
          378,
          1.4346
        ],
        [
          379,
          1.4345
        ],
        [
          380,
          1.4346
        ],
        [
          381,
          1.4346
        ],
        [
          382,
          1.4346
        ],
        [
          383,
          1.4347
        ],
        [
          384,
          1.4347
        ],
        [
          385,
          1.4346
        ],
        [
          386,
          1.4346
        ],
        [
          387,
          1.4347
        ],
        [
          388,
          1.4348
        ],
        [
          389,
          1.4348
        ],
        [
          390,
          1.4348
        ],
        [
          391,
          1.4348
        ],
        [
          392,
          1.4347
        ],
        [
          393,
          1.4347
        ],
        [
          394,
          1.4348
        ],
        [
          395,
          1.4346
        ],
        [
          396,
          1.4347
        ],
        [
          397,
          1.4347
        ],
        [
          398,
          1.4346
        ],
        [
          399,
          1.4346
        ],
        [
          400,
          1.4347
        ],
        [
          401,
          1.4346
        ],
        [
          402,
          1.4346
        ],
        [
          403,
          1.4346
        ],
        [
          404,
          1.4346
        ],
        [
          405,
          1.4346
        ],
        [
          406,
          1.4347
        ],
        [
          407,
          1.4346
        ],
        [
          408,
          1.4346
        ],
        [
          409,
          1.4347
        ],
        [
          410,
          1.4347
        ],
        [
          411,
          1.4346
        ],
        [
          412,
          1.4345
        ],
        [
          413,
          1.4346
        ],
        [
          414,
          1.4346
        ],
        [
          415,
          1.4346
        ],
        [
          416,
          1.4346
        ],
        [
          417,
          1.4346
        ],
        [
          418,
          1.4346
        ],
        [
          419,
          1.4347
        ],
        [
          420,
          1.4346
        ],
        [
          421,
          1.4348
        ],
        [
          422,
          1.4348
        ],
        [
          423,
          1.4347
        ],
        [
          424,
          1.4348
        ],
        [
          425,
          1.4348
        ],
        [
          426,
          1.4349
        ],
        [
          427,
          1.4349
        ],
        [
          428,
          1.4349
        ],
        [
          429,
          1.4349
        ],
        [
          430,
          1.4349
        ],
        [
          431,
          1.4349
        ],
        [
          432,
          1.4348
        ],
        [
          433,
          1.4347
        ],
        [
          434,
          1.4348
        ],
        [
          435,
          1.4349
        ],
        [
          436,
          1.4349
        ],
        [
          437,
          1.435
        ],
        [
          438,
          1.435
        ],
        [
          439,
          1.435
        ],
        [
          440,
          1.435
        ],
        [
          441,
          1.4351
        ],
        [
          442,
          1.4351
        ],
        [
          443,
          1.4351
        ],
        [
          444,
          1.435
        ],
        [
          445,
          1.4351
        ],
        [
          446,
          1.4351
        ],
        [
          447,
          1.4351
        ],
        [
          448,
          1.4351
        ],
        [
          449,
          1.435
        ],
        [
          450,
          1.435
        ],
        [
          451,
          1.435
        ],
        [
          452,
          1.4349
        ],
        [
          453,
          1.4349
        ],
        [
          454,
          1.4348
        ],
        [
          455,
          1.4348
        ],
        [
          456,
          1.4349
        ],
        [
          457,
          1.4349
        ],
        [
          458,
          1.4351
        ],
        [
          459,
          1.4351
        ],
        [
          460,
          1.435
        ],
        [
          461,
          1.4351
        ],
        [
          462,
          1.4351
        ],
        [
          463,
          1.4351
        ],
        [
          464,
          1.4349
        ],
        [
          465,
          1.4349
        ],
        [
          466,
          1.4349
        ],
        [
          467,
          1.435
        ],
        [
          468,
          1.4351
        ],
        [
          469,
          1.4351
        ],
        [
          470,
          1.4352
        ],
        [
          471,
          1.4353
        ],
        [
          472,
          1.4353
        ],
        [
          473,
          1.4353
        ],
        [
          474,
          1.4353
        ],
        [
          475,
          1.4353
        ],
        [
          476,
          1.4353
        ],
        [
          477,
          1.4354
        ],
        [
          478,
          1.4355
        ],
        [
          479,
          1.4355
        ],
        [
          480,
          1.4354
        ],
        [
          481,
          1.4355
        ],
        [
          482,
          1.4357
        ],
        [
          483,
          1.4355
        ],
        [
          484,
          1.4357
        ],
        [
          485,
          1.4357
        ],
        [
          486,
          1.4358
        ],
        [
          487,
          1.4358
        ],
        [
          488,
          1.4358
        ],
        [
          489,
          1.4359
        ],
        [
          490,
          1.436
        ],
        [
          491,
          1.4359
        ],
        [
          492,
          1.4359
        ],
        [
          493,
          1.4358
        ],
        [
          494,
          1.4358
        ],
        [
          495,
          1.4357
        ],
        [
          496,
          1.4357
        ],
        [
          497,
          1.4355
        ],
        [
          498,
          1.4355
        ],
        [
          499,
          1.4355
        ],
        [
          500,
          1.4354
        ],
        [
          501,
          1.4354
        ],
        [
          502,
          1.4353
        ],
        [
          503,
          1.4353
        ],
        [
          504,
          1.4353
        ],
        [
          505,
          1.4354
        ],
        [
          506,
          1.4354
        ],
        [
          507,
          1.4353
        ],
        [
          508,
          1.4354
        ],
        [
          509,
          1.4355
        ],
        [
          510,
          1.4354
        ],
        [
          511,
          1.4353
        ],
        [
          512,
          1.4353
        ],
        [
          513,
          1.4355
        ],
        [
          514,
          1.4353
        ],
        [
          515,
          1.4353
        ],
        [
          516,
          1.4354
        ],
        [
          517,
          1.4354
        ],
        [
          518,
          1.4355
        ],
        [
          519,
          1.4355
        ],
        [
          520,
          1.4357
        ],
        [
          521,
          1.4357
        ],
        [
          522,
          1.4358
        ],
        [
          523,
          1.4357
        ],
        [
          524,
          1.4356
        ],
        [
          525,
          1.4356
        ],
        [
          526,
          1.4356
        ],
        [
          527,
          1.436
        ],
        [
          528,
          1.4358
        ],
        [
          529,
          1.4359
        ],
        [
          530,
          1.4359
        ],
        [
          531,
          1.4358
        ],
        [
          532,
          1.4358
        ],
        [
          533,
          1.4358
        ],
        [
          534,
          1.4359
        ],
        [
          535,
          1.4361
        ],
        [
          536,
          1.4359
        ],
        [
          537,
          1.436
        ],
        [
          538,
          1.436
        ],
        [
          539,
          1.4361
        ],
        [
          540,
          1.4361
        ],
        [
          541,
          1.4361
        ],
        [
          542,
          1.436
        ],
        [
          543,
          1.4362
        ],
        [
          544,
          1.436
        ],
        [
          545,
          1.436
        ],
        [
          546,
          1.436
        ],
        [
          547,
          1.4361
        ],
        [
          548,
          1.436
        ],
        [
          549,
          1.436
        ],
        [
          550,
          1.4361
        ],
        [
          551,
          1.436
        ],
        [
          552,
          1.4362
        ],
        [
          553,
          1.4363
        ],
        [
          553,
          1.4362
        ],
        [
          554,
          1.4361
        ],
        [
          555,
          1.436
        ],
        [
          556,
          1.4358
        ],
        [
          557,
          1.4357
        ],
        [
          558,
          1.4355
        ],
        [
          559,
          1.4355
        ],
        [
          560,
          1.4355
        ],
        [
          561,
          1.4354
        ],
        [
          562,
          1.4354
        ],
        [
          563,
          1.4354
        ],
        [
          564,
          1.4353
        ],
        [
          565,
          1.4352
        ],
        [
          566,
          1.4352
        ],
        [
          567,
          1.4352
        ],
        [
          568,
          1.4352
        ],
        [
          569,
          1.4353
        ],
        [
          570,
          1.4351
        ],
        [
          571,
          1.4351
        ],
        [
          572,
          1.4353
        ],
        [
          573,
          1.4351
        ],
        [
          574,
          1.4351
        ],
        [
          575,
          1.4351
        ],
        [
          576,
          1.435
        ],
        [
          577,
          1.4351
        ],
        [
          578,
          1.4351
        ],
        [
          579,
          1.4352
        ],
        [
          580,
          1.4352
        ],
        [
          581,
          1.4352
        ],
        [
          582,
          1.435
        ],
        [
          583,
          1.4348
        ],
        [
          584,
          1.4349
        ],
        [
          585,
          1.4349
        ],
        [
          586,
          1.435
        ],
        [
          587,
          1.4349
        ],
        [
          588,
          1.435
        ],
        [
          589,
          1.4351
        ],
        [
          590,
          1.4351
        ],
        [
          591,
          1.435
        ],
        [
          592,
          1.435
        ],
        [
          593,
          1.435
        ],
        [
          594,
          1.4348
        ],
        [
          595,
          1.4348
        ],
        [
          596,
          1.4348
        ],
        [
          597,
          1.4347
        ],
        [
          598,
          1.4347
        ],
        [
          599,
          1.4347
        ],
        [
          600,
          1.4347
        ],
        [
          601,
          1.4346
        ],
        [
          602,
          1.4346
        ],
        [
          603,
          1.4346
        ],
        [
          604,
          1.4346
        ],
        [
          605,
          1.4347
        ],
        [
          606,
          1.4347
        ],
        [
          607,
          1.4346
        ],
        [
          608,
          1.4346
        ],
        [
          609,
          1.4346
        ],
        [
          610,
          1.4346
        ],
        [
          611,
          1.4347
        ],
        [
          612,
          1.4347
        ],
        [
          613,
          1.4347
        ],
        [
          614,
          1.4346
        ],
        [
          615,
          1.4347
        ],
        [
          616,
          1.4346
        ],
        [
          617,
          1.4347
        ],
        [
          618,
          1.4347
        ],
        [
          619,
          1.4347
        ],
        [
          620,
          1.4348
        ],
        [
          621,
          1.4347
        ],
        [
          622,
          1.4348
        ],
        [
          623,
          1.4348
        ],
        [
          624,
          1.4348
        ],
        [
          625,
          1.4348
        ],
        [
          626,
          1.4348
        ],
        [
          627,
          1.4349
        ],
        [
          628,
          1.4349
        ],
        [
          629,
          1.4349
        ],
        [
          630,
          1.4347
        ],
        [
          631,
          1.4347
        ],
        [
          632,
          1.4346
        ],
        [
          633,
          1.4346
        ],
        [
          634,
          1.4347
        ],
        [
          635,
          1.4348
        ],
        [
          636,
          1.4347
        ],
        [
          637,
          1.4348
        ],
        [
          638,
          1.4348
        ],
        [
          639,
          1.4349
        ],
        [
          640,
          1.4349
        ],
        [
          641,
          1.4348
        ],
        [
          642,
          1.4349
        ],
        [
          643,
          1.435
        ],
        [
          644,
          1.4349
        ],
        [
          645,
          1.4348
        ],
        [
          646,
          1.4348
        ],
        [
          647,
          1.4349
        ],
        [
          648,
          1.4349
        ],
        [
          649,
          1.4348
        ],
        [
          650,
          1.4349
        ],
        [
          651,
          1.4349
        ],
        [
          652,
          1.4349
        ],
        [
          653,
          1.4349
        ],
        [
          654,
          1.4348
        ],
        [
          655,
          1.4349
        ],
        [
          656,
          1.4349
        ],
        [
          657,
          1.4349
        ],
        [
          658,
          1.4349
        ],
        [
          659,
          1.4349
        ],
        [
          660,
          1.4349
        ],
        [
          661,
          1.4349
        ],
        [
          662,
          1.4349
        ],
        [
          663,
          1.4349
        ],
        [
          664,
          1.4347
        ],
        [
          665,
          1.4347
        ],
        [
          666,
          1.4346
        ],
        [
          667,
          1.4348
        ],
        [
          668,
          1.4348
        ],
        [
          669,
          1.435
        ],
        [
          670,
          1.435
        ],
        [
          671,
          1.4349
        ],
        [
          672,
          1.4347
        ],
        [
          673,
          1.4345
        ],
        [
          674,
          1.4346
        ],
        [
          675,
          1.4346
        ],
        [
          676,
          1.4346
        ],
        [
          677,
          1.4345
        ],
        [
          678,
          1.4343
        ],
        [
          679,
          1.4343
        ],
        [
          680,
          1.4342
        ],
        [
          681,
          1.4342
        ],
        [
          682,
          1.4341
        ],
        [
          683,
          1.434
        ],
        [
          684,
          1.4342
        ],
        [
          685,
          1.4341
        ],
        [
          686,
          1.4342
        ],
        [
          687,
          1.4343
        ],
        [
          688,
          1.4343
        ],
        [
          689,
          1.4342
        ],
        [
          690,
          1.4342
        ],
        [
          691,
          1.4342
        ],
        [
          692,
          1.4342
        ],
        [
          693,
          1.4342
        ],
        [
          694,
          1.4342
        ],
        [
          695,
          1.4342
        ],
        [
          696,
          1.4341
        ],
        [
          697,
          1.4342
        ],
        [
          698,
          1.4344
        ],
        [
          699,
          1.4343
        ],
        [
          700,
          1.4344
        ],
        [
          701,
          1.4344
        ],
        [
          702,
          1.4343
        ],
        [
          703,
          1.4343
        ],
        [
          704,
          1.4343
        ],
        [
          705,
          1.4344
        ],
        [
          706,
          1.4344
        ],
        [
          707,
          1.4343
        ],
        [
          708,
          1.4341
        ],
        [
          709,
          1.4341
        ],
        [
          710,
          1.4341
        ],
        [
          711,
          1.434
        ],
        [
          712,
          1.4339
        ],
        [
          713,
          1.4338
        ],
        [
          714,
          1.4336
        ],
        [
          715,
          1.4335
        ],
        [
          716,
          1.4333
        ],
        [
          717,
          1.4333
        ],
        [
          718,
          1.4336
        ],
        [
          719,
          1.4335
        ],
        [
          720,
          1.4334
        ],
        [
          721,
          1.4335
        ],
        [
          722,
          1.4336
        ],
        [
          723,
          1.4336
        ],
        [
          724,
          1.4336
        ],
        [
          725,
          1.4337
        ],
        [
          726,
          1.4337
        ],
        [
          727,
          1.4336
        ],
        [
          728,
          1.4336
        ],
        [
          729,
          1.4338
        ],
        [
          730,
          1.4337
        ],
        [
          731,
          1.4338
        ],
        [
          732,
          1.4339
        ],
        [
          733,
          1.4341
        ],
        [
          734,
          1.4341
        ],
        [
          735,
          1.4341
        ],
        [
          736,
          1.434
        ],
        [
          737,
          1.434
        ],
        [
          738,
          1.4339
        ],
        [
          739,
          1.4339
        ],
        [
          740,
          1.4339
        ],
        [
          741,
          1.434
        ],
        [
          742,
          1.4341
        ],
        [
          743,
          1.4341
        ],
        [
          744,
          1.4342
        ],
        [
          745,
          1.4341
        ],
        [
          746,
          1.4341
        ],
        [
          747,
          1.4339
        ],
        [
          748,
          1.434
        ],
        [
          749,
          1.4341
        ],
        [
          750,
          1.434
        ],
        [
          751,
          1.4342
        ],
        [
          752,
          1.4342
        ],
        [
          753,
          1.4342
        ],
        [
          754,
          1.4343
        ],
        [
          755,
          1.4343
        ],
        [
          756,
          1.4343
        ],
        [
          757,
          1.4341
        ],
        [
          758,
          1.4341
        ],
        [
          759,
          1.4341
        ],
        [
          760,
          1.434
        ],
        [
          761,
          1.4341
        ],
        [
          762,
          1.4341
        ],
        [
          763,
          1.4341
        ],
        [
          764,
          1.4341
        ],
        [
          765,
          1.4341
        ],
        [
          766,
          1.4341
        ],
        [
          767,
          1.4342
        ],
        [
          768,
          1.4342
        ],
        [
          769,
          1.4341
        ],
        [
          770,
          1.4341
        ],
        [
          771,
          1.4342
        ],
        [
          772,
          1.4342
        ],
        [
          773,
          1.4342
        ],
        [
          774,
          1.4341
        ],
        [
          775,
          1.4341
        ],
        [
          776,
          1.4341
        ],
        [
          777,
          1.4342
        ],
        [
          778,
          1.4343
        ],
        [
          779,
          1.4342
        ],
        [
          780,
          1.4341
        ],
        [
          781,
          1.4338
        ],
        [
          782,
          1.4337
        ],
        [
          783,
          1.4336
        ],
        [
          784,
          1.4335
        ],
        [
          785,
          1.4335
        ],
        [
          786,
          1.4336
        ],
        [
          787,
          1.4334
        ],
        [
          788,
          1.4333
        ],
        [
          789,
          1.4333
        ],
        [
          790,
          1.4332
        ],
        [
          791,
          1.4331
        ],
        [
          791,
          1.4331
        ],
        [
          792,
          1.4332
        ],
        [
          793,
          1.4334
        ],
        [
          794,
          1.4335
        ],
        [
          795,
          1.4334
        ],
        [
          796,
          1.4334
        ],
        [
          797,
          1.4336
        ],
        [
          798,
          1.4337
        ],
        [
          799,
          1.4339
        ],
        [
          800,
          1.4338
        ],
        [
          801,
          1.4337
        ],
        [
          802,
          1.4337
        ],
        [
          803,
          1.4337
        ],
        [
          804,
          1.4337
        ],
        [
          805,
          1.4339
        ],
        [
          806,
          1.4338
        ],
        [
          807,
          1.4339
        ],
        [
          808,
          1.434
        ],
        [
          809,
          1.4339
        ],
        [
          810,
          1.4338
        ],
        [
          811,
          1.4338
        ],
        [
          812,
          1.4338
        ],
        [
          813,
          1.4337
        ],
        [
          814,
          1.4338
        ],
        [
          815,
          1.4338
        ],
        [
          816,
          1.434
        ],
        [
          817,
          1.4339
        ],
        [
          818,
          1.434
        ],
        [
          819,
          1.434
        ],
        [
          820,
          1.434
        ],
        [
          821,
          1.434
        ],
        [
          822,
          1.434
        ],
        [
          823,
          1.4341
        ],
        [
          824,
          1.4342
        ],
        [
          825,
          1.4342
        ],
        [
          826,
          1.4341
        ],
        [
          827,
          1.4341
        ],
        [
          828,
          1.434
        ],
        [
          829,
          1.4341
        ],
        [
          830,
          1.4342
        ],
        [
          831,
          1.4342
        ],
        [
          832,
          1.4342
        ],
        [
          833,
          1.434
        ],
        [
          834,
          1.4341
        ],
        [
          835,
          1.4341
        ],
        [
          836,
          1.434
        ],
        [
          837,
          1.4341
        ],
        [
          838,
          1.434
        ],
        [
          839,
          1.4338
        ],
        [
          840,
          1.4339
        ],
        [
          841,
          1.4338
        ],
        [
          842,
          1.434
        ],
        [
          843,
          1.4342
        ],
        [
          844,
          1.434
        ],
        [
          845,
          1.434
        ],
        [
          846,
          1.4339
        ],
        [
          847,
          1.434
        ],
        [
          848,
          1.434
        ],
        [
          849,
          1.4341
        ],
        [
          850,
          1.4341
        ],
        [
          851,
          1.4341
        ],
        [
          852,
          1.4341
        ],
        [
          853,
          1.434
        ],
        [
          854,
          1.434
        ],
        [
          855,
          1.4341
        ],
        [
          856,
          1.434
        ],
        [
          857,
          1.4339
        ],
        [
          858,
          1.4338
        ],
        [
          859,
          1.4337
        ],
        [
          860,
          1.4336
        ],
        [
          861,
          1.4339
        ],
        [
          862,
          1.4338
        ],
        [
          863,
          1.4339
        ],
        [
          864,
          1.4337
        ],
        [
          865,
          1.4335
        ],
        [
          866,
          1.4337
        ],
        [
          867,
          1.4336
        ],
        [
          868,
          1.4336
        ],
        [
          869,
          1.4336
        ],
        [
          870,
          1.4335
        ],
        [
          871,
          1.4334
        ],
        [
          872,
          1.4334
        ],
        [
          873,
          1.4338
        ],
        [
          874,
          1.4338
        ],
        [
          875,
          1.434
        ],
        [
          876,
          1.4342
        ],
        [
          877,
          1.434
        ],
        [
          878,
          1.434
        ],
        [
          879,
          1.434
        ],
        [
          880,
          1.4339
        ],
        [
          881,
          1.434
        ],
        [
          882,
          1.434
        ],
        [
          883,
          1.434
        ],
        [
          884,
          1.434
        ],
        [
          885,
          1.434
        ],
        [
          886,
          1.4341
        ],
        [
          887,
          1.4342
        ],
        [
          888,
          1.4342
        ],
        [
          889,
          1.4343
        ],
        [
          890,
          1.4343
        ],
        [
          891,
          1.4343
        ],
        [
          892,
          1.4343
        ],
        [
          893,
          1.4342
        ],
        [
          894,
          1.4342
        ],
        [
          895,
          1.4343
        ],
        [
          896,
          1.4342
        ],
        [
          897,
          1.4342
        ],
        [
          898,
          1.4342
        ],
        [
          899,
          1.4344
        ],
        [
          900,
          1.4343
        ],
        [
          901,
          1.4345
        ],
        [
          902,
          1.4344
        ],
        [
          903,
          1.4344
        ],
        [
          904,
          1.4345
        ],
        [
          905,
          1.4344
        ],
        [
          906,
          1.4344
        ],
        [
          907,
          1.4343
        ],
        [
          908,
          1.4343
        ],
        [
          909,
          1.434
        ],
        [
          910,
          1.4341
        ],
        [
          911,
          1.4342
        ],
        [
          912,
          1.4341
        ],
        [
          913,
          1.4342
        ],
        [
          914,
          1.4343
        ],
        [
          915,
          1.4341
        ],
        [
          916,
          1.4341
        ],
        [
          917,
          1.4342
        ],
        [
          918,
          1.4342
        ],
        [
          919,
          1.4342
        ],
        [
          920,
          1.4341
        ],
        [
          921,
          1.434
        ],
        [
          922,
          1.4339
        ],
        [
          923,
          1.434
        ],
        [
          924,
          1.434
        ],
        [
          925,
          1.434
        ],
        [
          926,
          1.434
        ],
        [
          927,
          1.434
        ],
        [
          928,
          1.4339
        ],
        [
          929,
          1.434
        ],
        [
          930,
          1.434
        ],
        [
          931,
          1.434
        ],
        [
          932,
          1.4339
        ],
        [
          933,
          1.4339
        ],
        [
          934,
          1.4339
        ],
        [
          935,
          1.434
        ],
        [
          936,
          1.4341
        ],
        [
          937,
          1.4341
        ],
        [
          938,
          1.4341
        ],
        [
          939,
          1.4341
        ],
        [
          940,
          1.4341
        ],
        [
          941,
          1.4342
        ],
        [
          942,
          1.4341
        ],
        [
          943,
          1.4341
        ],
        [
          944,
          1.434
        ],
        [
          945,
          1.4339
        ],
        [
          946,
          1.4339
        ],
        [
          947,
          1.4336
        ],
        [
          948,
          1.4333
        ],
        [
          949,
          1.4332
        ],
        [
          950,
          1.4333
        ],
        [
          951,
          1.4335
        ],
        [
          952,
          1.4334
        ],
        [
          953,
          1.4333
        ],
        [
          954,
          1.4334
        ],
        [
          955,
          1.4338
        ],
        [
          956,
          1.4339
        ],
        [
          957,
          1.434
        ],
        [
          958,
          1.434
        ],
        [
          959,
          1.4338
        ],
        [
          960,
          1.4337
        ],
        [
          961,
          1.4335
        ],
        [
          962,
          1.4335
        ],
        [
          963,
          1.4334
        ],
        [
          964,
          1.4334
        ],
        [
          965,
          1.4334
        ],
        [
          966,
          1.4335
        ],
        [
          967,
          1.4335
        ],
        [
          968,
          1.4334
        ],
        [
          969,
          1.4334
        ],
        [
          970,
          1.4334
        ],
        [
          971,
          1.4335
        ],
        [
          972,
          1.4335
        ],
        [
          973,
          1.4335
        ],
        [
          974,
          1.4335
        ],
        [
          975,
          1.4334
        ],
        [
          976,
          1.4335
        ],
        [
          977,
          1.4336
        ],
        [
          978,
          1.4336
        ],
        [
          979,
          1.4337
        ],
        [
          980,
          1.4337
        ],
        [
          981,
          1.4338
        ],
        [
          982,
          1.4337
        ],
        [
          983,
          1.4334
        ],
        [
          984,
          1.4335
        ],
        [
          985,
          1.4336
        ],
        [
          986,
          1.4335
        ],
        [
          987,
          1.4335
        ],
        [
          988,
          1.4335
        ],
        [
          989,
          1.4335
        ],
        [
          990,
          1.4334
        ],
        [
          991,
          1.4333
        ],
        [
          992,
          1.4331
        ],
        [
          992,
          1.4332
        ],
        [
          993,
          1.4333
        ],
        [
          994,
          1.4335
        ],
        [
          995,
          1.4334
        ],
        [
          996,
          1.4335
        ],
        [
          997,
          1.4334
        ],
        [
          998,
          1.4334
        ],
        [
          999,
          1.4333
        ],
        [
          1000,
          1.4332
        ],
        [
          1001,
          1.4333
        ],
        [
          1002,
          1.4333
        ],
        [
          1003,
          1.4333
        ],
        [
          1004,
          1.4333
        ],
        [
          1005,
          1.4333
        ],
        [
          1006,
          1.4334
        ],
        [
          1007,
          1.4335
        ],
        [
          1008,
          1.4335
        ],
        [
          1009,
          1.4335
        ],
        [
          1010,
          1.4337
        ],
        [
          1011,
          1.4338
        ],
        [
          1012,
          1.4337
        ],
        [
          1013,
          1.4337
        ],
        [
          1014,
          1.4338
        ],
        [
          1015,
          1.4337
        ],
        [
          1016,
          1.4338
        ],
        [
          1017,
          1.4337
        ],
        [
          1018,
          1.4337
        ],
        [
          1019,
          1.4336
        ],
        [
          1020,
          1.4337
        ],
        [
          1021,
          1.4337
        ],
        [
          1022,
          1.4336
        ],
        [
          1023,
          1.4337
        ],
        [
          1024,
          1.4338
        ],
        [
          1025,
          1.4338
        ],
        [
          1026,
          1.4339
        ],
        [
          1027,
          1.4338
        ],
        [
          1028,
          1.4339
        ],
        [
          1029,
          1.4339
        ],
        [
          1030,
          1.4339
        ],
        [
          1031,
          1.4339
        ],
        [
          1032,
          1.434
        ],
        [
          1033,
          1.4339
        ],
        [
          1034,
          1.4339
        ],
        [
          1035,
          1.4339
        ],
        [
          1036,
          1.4339
        ],
        [
          1037,
          1.4338
        ],
        [
          1038,
          1.4338
        ],
        [
          1039,
          1.4338
        ],
        [
          1040,
          1.4338
        ],
        [
          1041,
          1.4339
        ],
        [
          1042,
          1.4338
        ],
        [
          1043,
          1.4338
        ],
        [
          1044,
          1.4338
        ],
        [
          1045,
          1.4338
        ],
        [
          1046,
          1.4338
        ],
        [
          1047,
          1.4338
        ],
        [
          1048,
          1.4337
        ],
        [
          1049,
          1.4338
        ],
        [
          1050,
          1.4337
        ],
        [
          1051,
          1.4336
        ],
        [
          1052,
          1.4337
        ],
        [
          1053,
          1.4335
        ],
        [
          1054,
          1.4335
        ]
      ],
      "id": "price:issueid:190168883",
      "type": "time"
    }
  ],
  "start": "2020-02-17T00:00:00",
  "end": "2020-02-17T17:34:01",
  "resolution": "PT1M"
}